zotero_bibtize/__init__.py
zotero_bibtize/bibkey_formatter.py
zotero_bibtize/cli.py
zotero_bibtize/zotero_bibtize.py
zotero_bibtize-0.1.0.dist-info/LICENSE
zotero_bibtize-0.1.0.dist-info/METADATA
zotero_bibtize-0.1.0.dist-info/WHEEL
zotero_bibtize-0.1.0.dist-info/entry_points.txt
zotero_bibtize-0.1.0.dist-info/top_level.txt
zotero_bibtize-0.1.0.dist-info/RECORD
