Metadata-Version: 2.1
Name: zotero-bibtize
Version: 0.1.0
Summary: Transform Zotero BibTex files to LaTeX friendly representation.
Home-page: https://github.com/astamminger/zotero-bibtize
Author: Andreas Stamminger
Author-email: stammingera@gmail.com
License: UNKNOWN
Keywords: Zotero Latex Bibtex
Platform: UNKNOWN
Classifier: Programming Language :: Python :: 3
Classifier: License :: OSI Approved :: MIT License
Classifier: Operating System :: OS Independent
Requires-Python: >=3
Requires-Dist: pathlib
Requires-Dist: click
